md2docx_python/__init__.py
md2docx_python/src/__init__.py
md2docx_python/src/docx2md_python.py
md2docx_python/src/md2docx_python.py
md2docx_python-1.0.0.dist-info/LICENSE
md2docx_python-1.0.0.dist-info/METADATA
md2docx_python-1.0.0.dist-info/WHEEL
md2docx_python-1.0.0.dist-info/top_level.txt
md2docx_python-1.0.0.dist-info/RECORD
