Metadata-Version: 2.1
Name: md2docx-python
Version: 1.0.0
Summary: Markdown to Word Converter.
Home-page: https://github.com/shloktech/md2docx-python
Author: Shlok Tadilkar
Author-email: shloktadilkar@gmail.com
License: MIT
Classifier: License :: OSI Approved :: MIT License
Classifier: Programming Language :: Python :: 3.9
Classifier: Operating System :: OS Independent
Requires-Python: >=3.9.0
License-File: LICENSE
Requires-Dist: markdown>=3.7
Requires-Dist: python-docx>=1.1.2
Requires-Dist: beautifulsoup4>=4.13.3
